openbb_finviz/__init__.py
openbb_finviz/models/__init__.py
openbb_finviz/models/compare_groups.py
openbb_finviz/models/equity_profile.py
openbb_finviz/models/equity_screener.py
openbb_finviz/models/key_metrics.py
openbb_finviz/models/price_performance.py
openbb_finviz/models/price_target.py
openbb_finviz/models/py.typed
openbb_finviz/py.typed
openbb_finviz/utils/__init__.py
openbb_finviz/utils/definitions.py
openbb_finviz/utils/presets/__init__.py
openbb_finviz/utils/presets/all_stocks.ini
openbb_finviz/utils/presets/analyst_strong_buy.ini
openbb_finviz/utils/presets/buffet_like.ini
openbb_finviz/utils/presets/bull_runs_over_10pct.ini
openbb_finviz/utils/presets/canslim.ini
openbb_finviz/utils/presets/cheap_dividend.ini
openbb_finviz/utils/presets/cheap_oversold.ini
openbb_finviz/utils/presets/continued_momentum.ini
openbb_finviz/utils/presets/death_cross.ini
openbb_finviz/utils/presets/fastgrowths.ini
openbb_finviz/utils/presets/golden_cross.ini
openbb_finviz/utils/presets/growth_stocks.ini
openbb_finviz/utils/presets/heavy_inst_ins.ini
openbb_finviz/utils/presets/large_cap_rsi20.ini
openbb_finviz/utils/presets/large_cap_rsi80.ini
openbb_finviz/utils/presets/modified_dreman.ini
openbb_finviz/utils/presets/modified_neff.ini
openbb_finviz/utils/presets/newhigh.ini
openbb_finviz/utils/presets/profitable_low_price_sales.ini
openbb_finviz/utils/presets/recent_growth_support.ini
openbb_finviz/utils/presets/screener_template.ini
openbb_finviz/utils/presets/short_squeeze.ini
openbb_finviz/utils/presets/undervalue.ini
openbb_finviz/utils/presets/weak_support_top_performers.ini
openbb_finviz/utils/py.typed
openbb_finviz/utils/screener_helper.py
openbb_finviz-1.4.1.dist-info/METADATA
openbb_finviz-1.4.1.dist-info/WHEEL
openbb_finviz-1.4.1.dist-info/entry_points.txt
openbb_finviz-1.4.1.dist-info/RECORD
